nodestream_plugin_neo4j/__init__.py
nodestream_plugin_neo4j/database_connector.py
nodestream_plugin_neo4j/extractor.py
nodestream_plugin_neo4j/ingest_query_builder.py
nodestream_plugin_neo4j/migrator.py
nodestream_plugin_neo4j/neo4j_database.py
nodestream_plugin_neo4j/query.py
nodestream_plugin_neo4j/query_executor.py
nodestream_plugin_neo4j/result.py
nodestream_plugin_neo4j/type_retriever.py
nodestream_plugin_neo4j-0.14.4.dist-info/METADATA
nodestream_plugin_neo4j-0.14.4.dist-info/WHEEL
nodestream_plugin_neo4j-0.14.4.dist-info/entry_points.txt
nodestream_plugin_neo4j-0.14.4.dist-info/RECORD
