Metadata-Version: 2.3
Name: nodestream-plugin-neo4j
Version: 0.14.4
Summary: 
Author: Zach Probst
Author-email: Zach_Probst@intuit.com
Requires-Python: >=3.10,<4.0
Classifier: Programming Language :: Python :: 3
Classifier: Programming Language :: Python :: 3.10
Classifier: Programming Language :: Python :: 3.11
Classifier: Programming Language :: Python :: 3.12
Classifier: Programming Language :: Python :: 3.13
Requires-Dist: cymple (>=0.11.0,<0.12.0)
Requires-Dist: dacite (>=1.9.2,<2.0.0)
Requires-Dist: neo4j (>=5.16.0,<6.0.0)
Requires-Dist: nodestream (>=0.14.14,<0.15.0)
